pretty_verbose/__init__.py
pretty_verbose/error_classes.py
pretty_verbose/logger_classes.py
pretty_verbose/messages_classes.py
pretty_verbose/processes_classes.py
pretty_verbose/constants/__init__.py
pretty_verbose/constants/colors.py
pretty_verbose/constants/error_codes.py
pretty_verbose-0.1.2.post4.dist-info/licenses/LICENSE
pretty_verbose-0.1.2.post4.dist-info/METADATA
pretty_verbose-0.1.2.post4.dist-info/WHEEL
pretty_verbose-0.1.2.post4.dist-info/top_level.txt
pretty_verbose-0.1.2.post4.dist-info/RECORD
