Metadata-Version: 2.4
Name: pretty_verbose
Version: 0.1.2.post4
Summary: Package for colored organized verbose printing in python.
Author-email: "C. Catalina M. Sarria" <ccatamorenos@gmail.com>
Maintainer-email: "C. Catalina M. Sarria" <ccatamorenos@gmail.com>
License: MIT License
Keywords: verbose,log,logger,colors,print
Requires-Python: >=3.8
License-File: LICENSE
Dynamic: license-file
